x_filter/__init__.py
x_filter/__main__.py
x_filter/_version.py
x_filter/aggregate.py
x_filter/ops.py
x_filter/reassign.py
x_filter/slice_mmap_arrays.py
x_filter/stats.py
x_filter/utils.py
x_filter-2.0.3.dist-info/LICENSE
x_filter-2.0.3.dist-info/METADATA
x_filter-2.0.3.dist-info/WHEEL
x_filter-2.0.3.dist-info/entry_points.txt
x_filter-2.0.3.dist-info/top_level.txt
x_filter-2.0.3.dist-info/RECORD
