Metadata-Version: 2.1
Name: x-filter
Version: 2.0.3
Summary: A simple tool to filter BLASTx m8 files using the FAMLI algorithm
Home-page: https://github.com/genomewalker/x-filter
Author: Antonio Fernandez-Guerra
Author-email: antonio@metagenomics.eu
License: GNUv3
Keywords: x-filter
Platform: UNKNOWN
Classifier: Programming Language :: Python :: 3.7
Classifier: Programming Language :: Python :: 3.8
Classifier: Programming Language :: Python :: 3.9
License-File: LICENSE
Requires-Dist: pandas>=2.2.3
Requires-Dist: tqdm>=4.62.3
Requires-Dist: numpy>=2.0.0
Requires-Dist: psutil
Requires-Dist: duckdb
Requires-Dist: numba
Requires-Dist: pyarrow
